jwt_validate/__init__.py
jwt_validate/config.py
jwt_validate/constants.py
jwt_validate/exceptions.py
jwt_validate/generate/generate_jwt.py
jwt_validate/utils.py
jwt_validate/validate/__init__.py
jwt_validate/validate/validate_jwt.py
jwt_validate-0.3.8.1.dist-info/METADATA
jwt_validate-0.3.8.1.dist-info/WHEEL
jwt_validate-0.3.8.1.dist-info/RECORD
