Metadata-Version: 2.1
Name: jwt-validate
Version: 0.3.8.1
Summary: Library for validation token JWT
License: Beerware
Author: Reinaldo Saraiva do Carmo
Author-email: reinaldo.carmo@luizalabs.com
Requires-Python: >=3.10,<4.0
Classifier: Development Status :: 5 - Production/Stable
Classifier: Framework :: FastAPI
Classifier: Intended Audience :: Developers
Classifier: License :: OSI Approved :: MIT License
Classifier: License :: Other/Proprietary License
Classifier: Natural Language :: English
Classifier: Operating System :: OS Independent
Classifier: Programming Language :: Python :: 3
Classifier: Programming Language :: Python :: 3.10
Classifier: Programming Language :: Python :: 3.11
Classifier: Programming Language :: Python :: 3
Classifier: Topic :: Internet :: WWW/HTTP :: WSGI :: Middleware
Requires-Dist: httpx (>=0.24.0,<0.25.0)
Requires-Dist: pyjwt[crypto] (>=2.7.0,<3.0.0)
Requires-Dist: pytest-env (>=0.8.1,<0.9.0)
Requires-Dist: python-dotenv (>=1.0.0,<2.0.0)
